slm_trainer/__init__.py
slm_trainer/trainer.py
slm_trainer/config/__init__.py
slm_trainer/config/model_configs.py
slm_trainer/config/training_configs.py
slm_trainer/model/__init__.py
slm_trainer/model/attention.py
slm_trainer/model/embeddings.py
slm_trainer/model/gpt.py
slm_trainer/model/transformer.py
slm_trainer/tokenizer/__init__.py
slm_trainer/tokenizer/tokenizer.py
slm_trainer/tokenizer/trainer.py
slm_trainer/training/__init__.py
slm_trainer/training/callbacks.py
slm_trainer/training/dataset.py
slm_trainer/training/trainer_engine.py
slm_trainer/utils/__init__.py
slm_trainer/utils/checkpoint.py
slm_trainer/utils/device.py
slm_trainer/utils/logging.py
slm_trainer-0.1.0.0.dist-info/licenses/LICENSE
slm_trainer-0.1.0.0.dist-info/METADATA
slm_trainer-0.1.0.0.dist-info/WHEEL
slm_trainer-0.1.0.0.dist-info/top_level.txt
slm_trainer-0.1.0.0.dist-info/RECORD
