Metadata-Version: 2.4
Name: slm-trainer
Version: 0.1.0.0
Summary: A Python library for training private Small Language Models
Home-page: https://github.com/yourusername/SLM-Trainer
Author: Your Name
Author-email: Your Name <your.email@example.com>
License-Expression: MIT
Project-URL: Homepage, https://github.com/yourusername/SLM-Trainer
Project-URL: Documentation, https://github.com/yourusername/SLM-Trainer#readme
Project-URL: Repository, https://github.com/yourusername/SLM-Trainer
Project-URL: Issues, https://github.com/yourusername/SLM-Trainer/issues
Keywords: pytorch,transformer,gpt,language-model,nlp,machine-learning
Classifier: Development Status :: 3 - Alpha
Classifier: Intended Audience :: Developers
Classifier: Intended Audience :: Science/Research
Classifier: Programming Language :: Python :: 3
Classifier: Programming Language :: Python :: 3.8
Classifier: Programming Language :: Python :: 3.9
Classifier: Programming Language :: Python :: 3.10
Classifier: Programming Language :: Python :: 3.11
Classifier: Programming Language :: Python :: 3.12
Classifier: Programming Language :: Python :: 3.13
Classifier: Topic :: Scientific/Engineering :: Artificial Intelligence
Classifier: Topic :: Software Development :: Libraries :: Python Modules
Requires-Python: >=3.8
License-File: LICENSE
Requires-Dist: torch>=2.0.0
Requires-Dist: sentencepiece>=0.1.99
Requires-Dist: numpy>=1.21.0
Requires-Dist: tqdm>=4.65.0
Provides-Extra: dev
Requires-Dist: pytest>=7.0.0; extra == "dev"
Requires-Dist: pytest-cov>=3.0.0; extra == "dev"
Requires-Dist: black>=22.0.0; extra == "dev"
Requires-Dist: flake8>=4.0.0; extra == "dev"
Requires-Dist: mypy>=0.950; extra == "dev"
Dynamic: author
Dynamic: home-page
Dynamic: license-file
Dynamic: requires-python
